{
  "SERVICES_EVENTS_ADMIN_SERVICE": [
    {
      "PutRequest": {
        "Item": {
          "partitionKey": {
            "S": "USER"
          },
          "sortKey": {
            "S": "USER#base-user-id"
          },
          "clientIds": {
            "SS": [
              "base-client-id"
            ]
          },
          "name": {
            "S": "Base User"
          },
          "createdOn": {
            "S": "2024-10-26T01:02:34"
          },
          "lastUpdatedOn": {
            "S": "2024-10-26T01:02:34"
          }
        }
      }
    }
  ]
}